dyepy.py
dyepy-1.0.1.dist-info/LICENSE
dyepy-1.0.1.dist-info/METADATA
dyepy-1.0.1.dist-info/WHEEL
dyepy-1.0.1.dist-info/top_level.txt
dyepy-1.0.1.dist-info/RECORD
