Metadata-Version: 2.1
Name: dyepy
Version: 1.0.1
Summary: A Python module for all colors and related functions
Home-page: https://github.com/SFM61319/DyePy
Author: SFM61319
Author-email: svasssakavi@gmail.com
License: MIT
Platform: UNKNOWN
Classifier: Programming Language :: Python :: 3
Classifier: License :: OSI Approved :: MIT License
Classifier: Operating System :: OS Independent
Requires-Python: >=3.6
